aind_data_transformation/__init__.py
aind_data_transformation/core.py
aind_data_transformation-0.1.2.dist-info/LICENSE
aind_data_transformation-0.1.2.dist-info/METADATA
aind_data_transformation-0.1.2.dist-info/WHEEL
aind_data_transformation-0.1.2.dist-info/top_level.txt
aind_data_transformation-0.1.2.dist-info/RECORD
